glcm/__init__.py
test/__init__.py
test/bounds_test.py
glcmbin5-0.1.4.dist-info/LICENSE
glcmbin5-0.1.4.dist-info/METADATA
glcmbin5-0.1.4.dist-info/WHEEL
glcmbin5-0.1.4.dist-info/top_level.txt
glcmbin5-0.1.4.dist-info/RECORD
