Metadata-Version: 2.1
Name: glcmbin5
Version: 0.1.4
Summary: Binned Cython 5 Feature GLCM
Home-page: https://github.com/Eve-ning/glcm
Author: evening
Author-email: dev_evening@hotmail.com
License: UNKNOWN
Platform: UNKNOWN
Classifier: Development Status :: 3 - Alpha
Classifier: Programming Language :: Python :: 3
Classifier: License :: OSI Approved :: MIT License
Classifier: Operating System :: OS Independent
Requires-Python: >=3.7
Requires-Dist: numpy
Requires-Dist: tqdm
Requires-Dist: cython
